<databaseChangeLog xmlns="http://www.liquibase.org/xml/ns/dbchangelog"
	xmlns:xsi="http://www.w3.org/2001/XMLSchema-instance" xmlns:ext="http://www.liquibase.org/xml/ns/dbchangelog-ext"
	xsi:schemaLocation="http://www.liquibase.org/xml/ns/dbchangelog http://www.liquibase.org/xml/ns/dbchangelog/dbchangelog-2.0.xsd http://www.liquibase.org/xml/ns/dbchangelog-ext http://www.liquibase.org/xml/ns/dbchangelog/dbchangelog-ext.xsd">

  <changeSet id="20161018-1440" author="micnice">
    <comment>Change component type combination name size limit to VARCHAR (250)</comment>
    <sql>
      ALTER TABLE ComponentTypeCombination MODIFY combinationName VARCHAR(255) NOT NULL;
    </sql>
  </changeSet>

  <changeSet id="20161017-1028" author="timler">
    <comment>Ensure that component type combination name is unique and not nullable </comment>
    <addUniqueConstraint tableName="ComponentTypeCombination" columnNames="combinationName"
      constraintName="ComponentTypeCombination_combinationName" />
    <addNotNullConstraint tableName="ComponentTypeCombination" columnName="combinationName"
      columnDataType="varchar(255)" />
  </changeSet>
  
</databaseChangeLog>